deeprob/__init__.py
deeprob/context.py
deeprob/flows/__init__.py
deeprob/flows/utils.py
deeprob/flows/layers/__init__.py
deeprob/flows/layers/autoregressive.py
deeprob/flows/layers/coupling.py
deeprob/flows/layers/densenet.py
deeprob/flows/layers/resnet.py
deeprob/flows/models/__init__.py
deeprob/flows/models/base.py
deeprob/flows/models/maf.py
deeprob/flows/models/realnvp.py
deeprob/spn/__init__.py
deeprob/spn/algorithms/__init__.py
deeprob/spn/algorithms/evaluation.py
deeprob/spn/algorithms/gradient.py
deeprob/spn/algorithms/inference.py
deeprob/spn/algorithms/moments.py
deeprob/spn/algorithms/sampling.py
deeprob/spn/algorithms/structure.py
deeprob/spn/layers/__init__.py
deeprob/spn/layers/dgcspn.py
deeprob/spn/layers/ratspn.py
deeprob/spn/learning/__init__.py
deeprob/spn/learning/em.py
deeprob/spn/learning/leaf.py
deeprob/spn/learning/learnspn.py
deeprob/spn/learning/wrappers.py
deeprob/spn/learning/xpc.py
deeprob/spn/learning/splitting/__init__.py
deeprob/spn/learning/splitting/cluster.py
deeprob/spn/learning/splitting/cols.py
deeprob/spn/learning/splitting/entropy.py
deeprob/spn/learning/splitting/gini.py
deeprob/spn/learning/splitting/gvs.py
deeprob/spn/learning/splitting/random.py
deeprob/spn/learning/splitting/rdc.py
deeprob/spn/learning/splitting/rows.py
deeprob/spn/models/__init__.py
deeprob/spn/models/dgcspn.py
deeprob/spn/models/ratspn.py
deeprob/spn/models/sklearn.py
deeprob/spn/structure/__init__.py
deeprob/spn/structure/cltree.py
deeprob/spn/structure/io.py
deeprob/spn/structure/leaf.py
deeprob/spn/structure/node.py
deeprob/spn/utils/__init__.py
deeprob/spn/utils/filter.py
deeprob/spn/utils/partitioning.py
deeprob/spn/utils/statistics.py
deeprob/spn/utils/validity.py
deeprob/torch/__init__.py
deeprob/torch/base.py
deeprob/torch/callbacks.py
deeprob/torch/constraints.py
deeprob/torch/datasets.py
deeprob/torch/initializers.py
deeprob/torch/metrics.py
deeprob/torch/routines.py
deeprob/torch/transforms.py
deeprob/torch/utils.py
deeprob/utils/__init__.py
deeprob_kit-1.1.0.dist-info/LICENSE
deeprob_kit-1.1.0.dist-info/METADATA
deeprob_kit-1.1.0.dist-info/WHEEL
deeprob_kit-1.1.0.dist-info/top_level.txt
deeprob_kit-1.1.0.dist-info/RECORD
