Metadata-Version: 2.1
Name: deeprob-kit
Version: 1.1.0
Summary: A Python Library for Deep Probabilistic Modeling
Home-page: https://github.com/deeprob-org/deeprob-kit
Author: Lorenzo Loconte, Gennaro Gala
Author-email: lorenzoloconte@outlook.it, g.gala@tue.nl
License: UNKNOWN
Platform: UNKNOWN
Classifier: Programming Language :: Python :: 3
Classifier: License :: OSI Approved :: MIT License
Classifier: Operating System :: OS Independent
Requires-Python: >=3.8
License-File: LICENSE
Requires-Dist: joblib
Requires-Dist: numpy
Requires-Dist: scipy
Requires-Dist: tqdm
Requires-Dist: torch
Requires-Dist: torchvision
Requires-Dist: scikit-learn
Requires-Dist: matplotlib
Requires-Dist: networkx
Requires-Dist: pydot
